tap_adwords/__init__.py
tap_adwords/metadata/accounts.json
tap_adwords/metadata/ad_groups.json
tap_adwords/metadata/ads.json
tap_adwords/metadata/campaigns.json
tap_adwords/schemas/accounts.json
tap_adwords/schemas/ad_groups.json
tap_adwords/schemas/ads.json
tap_adwords/schemas/campaigns.json
tap_adwords_velocity/__init__.py
tap_adwords_velocity-1.16.0.dist-info/LICENSE
tap_adwords_velocity-1.16.0.dist-info/METADATA
tap_adwords_velocity-1.16.0.dist-info/WHEEL
tap_adwords_velocity-1.16.0.dist-info/entry_points.txt
tap_adwords_velocity-1.16.0.dist-info/top_level.txt
tap_adwords_velocity-1.16.0.dist-info/RECORD
