Metadata-Version: 2.1
Name: tap-adwords-velocity
Version: 1.16.0
Summary: Singer.io tap for extracting data from the Adwords api
Home-page: http://singer.io
Author: Stitch
License: UNKNOWN
Platform: UNKNOWN
Classifier: Programming Language :: Python :: 3 :: Only
Requires-Dist: singer-python (==5.1.5)
Requires-Dist: requests (==2.20.0)
Requires-Dist: googleads (==17.0.0)
Requires-Dist: pytz (==2018.4)
Requires-Dist: zeep (==3.1.0)
Provides-Extra: dev
Requires-Dist: ipdb (==0.11) ; extra == 'dev'
Requires-Dist: pylint ; extra == 'dev'
Requires-Dist: nose ; extra == 'dev'
